termapp/__init__.py
termapp/__main__.py
termapp/_symbols.py
termapp/asyncio.py
termapp/stream.py
termapp/styles.py
termapp/sync.py
termapp-0.1.2.dist-info/LICENSE
termapp-0.1.2.dist-info/METADATA
termapp-0.1.2.dist-info/WHEEL
termapp-0.1.2.dist-info/top_level.txt
termapp-0.1.2.dist-info/zip-safe
termapp-0.1.2.dist-info/RECORD
