Metadata-Version: 2.1
Name: termapp
Version: 0.1.2
Summary: Library for writing simple terminal apps
Home-page: https://github.com/halimath/termapp
Author: Alexander Metzner
Author-email: alexander.metzner@gmail.com
License: Apache
Classifier: Development Status :: 4 - Beta
Classifier: Environment :: Console
Classifier: Intended Audience :: Developers
Classifier: License :: OSI Approved :: Apache Software License
Classifier: Operating System :: POSIX
Classifier: Programming Language :: Python :: 3.9
Classifier: Programming Language :: Python :: 3.10
Classifier: Topic :: Software Development :: User Interfaces
Classifier: Topic :: Terminals
Requires-Python: >=3.9
License-File: LICENSE
